minectl/__init__.py
minectl/alembic.ini
minectl/cli/__init__.py
minectl/cli/main.py
minectl/configs/__init__.py
minectl/schemas/__init__.py
minectl/tasks/__init__.py
minectl/utils/__init__.py
minectl-0.1.0.dist-info/entry_points.txt
minectl-0.1.0.dist-info/WHEEL
minectl-0.1.0.dist-info/METADATA
minectl-0.1.0.dist-info/RECORD
