Metadata-Version: 2.1
Name: minectl
Version: 0.1.0
Summary: InterMine automation helper
License: MIT
Author: Ankur Kumar
Author-email: ank@leoank.me
Requires-Python: >=3.8,<4.0
Classifier: License :: OSI Approved :: MIT License
Classifier: Programming Language :: Python :: 3
Classifier: Programming Language :: Python :: 3.10
Classifier: Programming Language :: Python :: 3.8
Classifier: Programming Language :: Python :: 3.9
Requires-Dist: PyYAML (>=5.4.1,<6.0.0)
Requires-Dist: blackcap
